ntia_conformance_checker/__init__.py
ntia_conformance_checker/base_checker.py
ntia_conformance_checker/cli_utils.py
ntia_conformance_checker/constants.py
ntia_conformance_checker/fsct_checker.py
ntia_conformance_checker/main.py
ntia_conformance_checker/ntia_checker.py
ntia_conformance_checker/report.py
ntia_conformance_checker/sbom_checker.py
ntia_conformance_checker/spdx3_utils.py
ntia_conformance_checker-4.1.1.dist-info/licenses/LICENSE
ntia_conformance_checker-4.1.1.dist-info/METADATA
ntia_conformance_checker-4.1.1.dist-info/WHEEL
ntia_conformance_checker-4.1.1.dist-info/entry_points.txt
ntia_conformance_checker-4.1.1.dist-info/top_level.txt
ntia_conformance_checker-4.1.1.dist-info/RECORD
