Metadata-Version: 2.4
Name: ntia_conformance_checker
Version: 4.1.1
Summary: Check SPDX SBOM for NTIA minimum elements and CISA baseline attributes
Author-email: Josh Lin <linynjosh@gmail.com>, John Speed Meyers <johnmeyersster@gmail.com>, Arthit Suriyawongkul <suriyawa@tcd.ie>
Maintainer-email: John Speed Meyers <johnmeyersster@gmail.com>, Gary O'Neall <gary@sourceauditor.com>, Josh Lin <linynjosh@gmail.com>, Arthit Suriyawongkul <suriyawa@tcd.ie>, SPDX group at the Linux Foundation and others <spdx-implementers+owner@lists.spdx.org>
License-Expression: Apache-2.0
Project-URL: Homepage, https://github.com/spdx/ntia-conformance-checker
Keywords: spdx,sbom,ntia,cisa,minimum elements,baseline attributes,software bill of materials,bill of materials,common SBOM,software package data exchange,software component transparency,supply chain security
Classifier: Intended Audience :: Developers
Classifier: Intended Audience :: System Administrators
Classifier: Programming Language :: Python :: 3.9
Classifier: Programming Language :: Python :: 3.10
Classifier: Programming Language :: Python :: 3.11
Classifier: Programming Language :: Python :: 3.12
Classifier: Programming Language :: Python :: 3.13
Classifier: Topic :: Security
Classifier: Topic :: Software Development :: Libraries :: Python Modules
Classifier: Topic :: System :: Systems Administration
Requires-Python: >=3.9
License-File: LICENSE
Requires-Dist: spdx-python-model==0.0.3
Requires-Dist: spdx-tools==0.8.3
Provides-Extra: dev
Requires-Dist: black>=25.9.0; extra == "dev"
Requires-Dist: mypy>=1.18.2; extra == "dev"
Requires-Dist: pylint>=3.3.9; extra == "dev"
Requires-Dist: pyrefly>=0.42.0; extra == "dev"
Requires-Dist: pyright>=1.1.407; extra == "dev"
Requires-Dist: pytype>=2024.9.13; extra == "dev"
Requires-Dist: ruff>=0.14.5; extra == "dev"
Provides-Extra: docs
Requires-Dist: sphinx>=7.4.7; extra == "docs"
Requires-Dist: sphinx-rtd-theme>=3.0.2; extra == "docs"
Provides-Extra: test
Requires-Dist: beartype==0.21.0; extra == "test"
Requires-Dist: coverage==7.10.7; extra == "test"
Requires-Dist: pytest==8.4.2; extra == "test"
Dynamic: license-file
